autonity/__init__.py
autonity/__version__.py
autonity/constants.py
autonity/factory.py
autonity/py.typed
autonity/contracts/__init__.py
autonity/contracts/accountability.py
autonity/contracts/acu.py
autonity/contracts/auctioneer.py
autonity/contracts/autonity.py
autonity/contracts/inflation_controller.py
autonity/contracts/liquid_logic.py
autonity/contracts/omission_accountability.py
autonity/contracts/oracle.py
autonity/contracts/stabilization.py
autonity/contracts/supply_control.py
autonity/contracts/upgrade_manager.py
autonity-6.0.0.dist-info/METADATA
autonity-6.0.0.dist-info/WHEEL
autonity-6.0.0.dist-info/licenses/LICENSE
autonity-6.0.0.dist-info/RECORD
