Metadata-Version: 2.4
Name: autonity
Version: 6.0.0
Summary: Python SDK for Autonity
Project-URL: Homepage, https://github.com/autonity/autonity.py
Project-URL: Source, https://github.com/autonity/autonity.py
Project-URL: Issues, https://github.com/autonity/autonity.py/issues
Project-URL: Changes, https://github.com/autonity/autonity.py/blob/master/CHANGELOG.md
License-Expression: MIT
License-File: LICENSE
Keywords: autonity,client,library,rpc,web3
Classifier: Development Status :: 4 - Beta
Classifier: License :: OSI Approved :: MIT License
Classifier: Programming Language :: Python
Classifier: Programming Language :: Python :: 3.9
Classifier: Programming Language :: Python :: 3.10
Classifier: Programming Language :: Python :: 3.11
Classifier: Programming Language :: Python :: 3.12
Classifier: Programming Language :: Python :: 3.13
Requires-Python: >=3.9
Requires-Dist: plum-dispatch==2.5.4
Requires-Dist: semver==3.0.2
Requires-Dist: web3==7.12.0
